deephaven_plugin_plotly_js/__distribution_path__/LICENSE
deephaven_plugin_plotly_js/__distribution_path__/README.md
deephaven_plugin_plotly_js/__distribution_path__/dist/index.js
deephaven_plugin_plotly_js/__distribution_path__/dist/index.js.LICENSE.txt
deephaven_plugin_plotly_js/__distribution_path__/dist/index.js.map
deephaven_plugin_plotly_js/__distribution_path__/package.json
deephaven_plugin_plotly_js/__info__.py
deephaven_plugin_plotly_js/__init__.py
deephaven_plugin_plotly_js-0.1.0.dev7.dist-info/entry_points.txt
deephaven_plugin_plotly_js-0.1.0.dev7.dist-info/WHEEL
deephaven_plugin_plotly_js-0.1.0.dev7.dist-info/METADATA
deephaven_plugin_plotly_js-0.1.0.dev7.dist-info/licenses/LICENSE
deephaven_plugin_plotly_js-0.1.0.dev7.dist-info/RECORD
