Metadata-Version: 2.1
Name: deephaven-plugin-plotly-js
Version: 0.1.0.dev7
Summary: Deephaven Plotly JS Plugin
License: Apache-2.0
Keywords: deephaven,plotly,js,plugin
Author-email: Devin Smith <devinsmith@deephaven.io>
Maintainer-email: Devin Smith <devinsmith@deephaven.io>
Requires-Python: >=3.9
Requires-Dist: deephaven-plugin>=0.4.0.dev0
Project-URL: Bug Tracker, https://github.com/deephaven/deephaven-plugin-plotly-js/issues
Project-URL: Homepage, https://github.com/deephaven/deephaven-plugin-plotly-js
Project-URL: Source Code, https://github.com/deephaven/deephaven-plugin-plotly-js
